educhateval/.DS_Store
educhateval/__init__.py
educhateval/chat_ui.py
educhateval/classification_utils.py
educhateval/core.py
educhateval/descriptive_results/.DS_Store
educhateval/descriptive_results/__init__.py
educhateval/descriptive_results/display_results.py
educhateval/dialogue_classification/.DS_Store
educhateval/dialogue_classification/__init__.py
educhateval/dialogue_classification/train_classifier.py
educhateval/dialogue_generation/.DS_Store
educhateval/dialogue_generation/__init__.py
educhateval/dialogue_generation/agents/base_agent.py
educhateval/dialogue_generation/chat.py
educhateval/dialogue_generation/chat_model_interface.py
educhateval/dialogue_generation/models/wrap_huggingface.py
educhateval/dialogue_generation/models/wrap_micr.py
educhateval/dialogue_generation/simulate_dialogue.py
educhateval/dialogue_generation/txt_llm_inputs/prompt_loader.py
educhateval/dialogue_generation/txt_llm_inputs/prompt_wrapper.py
educhateval/dialogue_generation/txt_llm_inputs/student_seed_messages.yaml
educhateval/dialogue_generation/txt_llm_inputs/student_seed_overall.yaml
educhateval/dialogue_generation/txt_llm_inputs/system_prompts.yaml
educhateval/framework_generation/.DS_Store
educhateval/framework_generation/__init__.py
educhateval/framework_generation/outline_prompts/prompt_default_4types.py
educhateval/framework_generation/outline_prompts/prompt_feedback.py
educhateval/framework_generation/outline_synth_LMSRIPT.py
educhateval/framework_generation/train_tinylabel_classifier.py
educhateval-0.1.10.dist-info/LICENSE
educhateval-0.1.10.dist-info/METADATA
educhateval-0.1.10.dist-info/WHEEL
educhateval-0.1.10.dist-info/entry_points.txt
educhateval-0.1.10.dist-info/RECORD
