Metadata-Version: 2.3
Name: educhateval
Version: 0.1.10
Summary: A pipeline and package to implement and evaluate LLM chat bot tutors in education.
License: MIT
Keywords: education,llm,chatbot,tutoring,ai in education
Author: Laura Wulff Paaby
Author-email: laurapaaby18@gmail.com
Requires-Python: >=3.12,<3.13
Classifier: Development Status :: 3 - Alpha
Classifier: Intended Audience :: Education
Classifier: Topic :: Education
Classifier: License :: OSI Approved :: MIT License
Classifier: Programming Language :: Python :: 3
Classifier: Programming Language :: Python :: 3.12
Provides-Extra: dev
Requires-Dist: accelerate (>=1.4.0,<2.0.0)
Requires-Dist: aiohttp (<3.11.13) ; extra == "dev"
Requires-Dist: black (>=25.1.0,<26.0.0) ; extra == "dev"
Requires-Dist: datasets (>=3.3.2,<4.0.0)
Requires-Dist: ipykernel (>=6.29.5,<7.0.0)
Requires-Dist: ipykernel (>=6.29.5,<7.0.0) ; extra == "dev"
Requires-Dist: ipywidgets (>=8.1.6,<9.0.0)
Requires-Dist: lmstudio (>=1.0.1,<2.0.0)
Requires-Dist: matplotlib (>=3.10.1,<4.0.0)
Requires-Dist: mkdocs (>=1.6.1,<2.0.0) ; extra == "dev"
Requires-Dist: mkdocs-glightbox (>=0.4.0,<0.5.0)
Requires-Dist: mkdocs-material (>=9.6.11,<10.0.0) ; extra == "dev"
Requires-Dist: mkdocs-mermaid2-plugin (>=1.2.1,<2.0.0)
Requires-Dist: mkdocstrings (>=0.29.1,<1.0.0) ; extra == "dev"
Requires-Dist: mlx-lm (>=0.22.2,<0.23.0)
Requires-Dist: notebook (>=7.4.0,<8.0.0)
Requires-Dist: numpy (>=2.2.3,<3.0.0)
Requires-Dist: optuna (>=4.2.1,<5.0.0)
Requires-Dist: optuna-integration (>=4.2.1,<5.0.0)
Requires-Dist: outlines (>=0.2.1,<0.3.0)
Requires-Dist: pandas (>=2.2.3,<3.0.0)
Requires-Dist: requests (>=2.32.3,<3.0.0)
Requires-Dist: scikit-learn (>=1.6.1,<2.0.0)
Requires-Dist: seaborn (>=0.13.2,<0.14.0)
Requires-Dist: sentencepiece (>=0.2.0,<0.3.0)
Requires-Dist: textual (>=3.0.1,<4.0.0)
Requires-Dist: toml (>=0.10.2,<0.11.0)
Requires-Dist: torch (>=2.6.0,<3.0.0)
Requires-Dist: transformers (>=4.49.0,<5.0.0)
Project-URL: Homepage, https://laurawpaaby.github.io/EduChatEval/
Project-URL: Issues, https://github.com/laurawpaaby/EduChatEval/issues
Project-URL: Repository, https://github.com/laurawpaaby/EduChatEval
